vineelapdf/__init__.py
vineelapdf/pdf2image.py
vineelapdf/pdf2text.py
vineelapdf-2.0.1.dist-info/licenses/LICENSE
vineelapdf-2.0.1.dist-info/METADATA
vineelapdf-2.0.1.dist-info/WHEEL
vineelapdf-2.0.1.dist-info/top_level.txt
vineelapdf-2.0.1.dist-info/RECORD
